{"symbol": "TRMK", "companyName": "Trustmark Corporation", "exchange": "Nasdaq Global Select", "industry": "Banks", "website": "http://www.trustmark.com", "description": "Trustmark Corp is a bank holding company. It operates through Trustmark National Bank providing financial services including Commercial Banking, Consumer Banking, Insurance, Wealth Management and Trust Services, and New Market Tax Credits.", "CEO": "Gerard R. Host", "issueType": "cs", "sector": "Financial Services", "tags": ["Financial Services", "Banks - Regional - US", "Banks"]}