{"symbol": "LKQ", "companyName": "LKQ Corporation", "exchange": "Nasdaq Global Select", "industry": "Autos", "website": "http://www.lkqcorp.com", "description": "LKQ Corp is a provider of alternative and mechanical replacement products. The company distributes vehicle replacement parts, components, and systems used in repair and maintenance as well as specialty products and accessories.", "CEO": "Dominick Zarcone", "issueType": "cs", "sector": "Consumer Cyclical", "tags": ["Consumer Cyclical", "Auto Parts", "Autos"]}