{"symbol": "PFSI", "companyName": "PennyMac Financial Services Inc. - Ordinary Shares", "exchange": "New York Stock Exchange", "industry": "Banks", "website": "http://www.pennymacfinancial.com", "description": "PennyMac Financial Services Inc provides mortgage loans to customers in the United States. The company's services span its main function of loan production and loan servicing which includes the recovery of loans and other related charges.", "CEO": "David Spector", "issueType": "cs", "sector": "Financial Services", "tags": ["Financial Services", "Specialty Finance", "Banks"]}