{"symbol": "PZD", "companyName": "Invesco Cleantech", "exchange": "NYSE Arca", "industry": "", "website": "http://www.invescopowershares.com", "description": "The investment seeks to track the investment results (before fees and expenses) of The Cleantech IndexTM.\n The fund generally will invest at least 90% of its total assets in securities that comprise the underlying index, which is designed to track the performance of publicly traded clean technology (or \"cleantech\") companies. Cleantech considers a company to be a cleantech company when it derives at least 50% of its revenues or operating profits from cleantech businesses.", "CEO": "", "issueType": "et", "sector": "", "tags": []}