{"symbol": "SMDD", "companyName": "UltraPro Short MidCap400", "exchange": "NYSE Arca", "industry": "", "website": "http://www.proshares.com", "description": "The investment seeks daily investment results, before fees and expenses, that correspond to three times the inverse (-3x) of the daily performance of the S&P MidCap 400\u00ae Index.\n The fund invests in financial instruments that ProShare Advisors believes, in combination, should produce daily returns consistent with the fund's investment objective. The index is a measure of mid-size company U.S. stock market performance. The fund is non-diversified.", "CEO": "", "issueType": "", "sector": "", "tags": []}