{"symbol": "GCOW", "companyName": "Pacer Global Cash Cows Dividend", "exchange": "Cboe Global Markets EDGX", "industry": "", "website": "http://www.paceretfs.com", "description": "The investment seeks to track the total return performance, before fees and expenses, of the Pacer Global Cash Cows Dividend Index.\n Under normal circumstances, the fund will invest at least 80% of its total assets (exclusive of collateral held from securities lending) in the components of the index and investments that have economic characteristics that are substantially identical to the economic characteristics of such component securities (e.g., depositary receipts). The index uses an objective, rules-based methodology to provide exposure to global companies with high dividend yields backed by a high free cash flow yield. The fund is non-diversified.", "CEO": "", "issueType": "", "sector": "", "tags": []}