{"symbol": "GNE", "companyName": "Genie Energy Ltd. Class B Stock", "exchange": "New York Stock Exchange", "industry": "Oil & Gas - E&P", "website": "http://www.genie.com", "description": "Genie Energy Ltd through its subsidiaries resells electricity and natural gas to residential and small business customers operating in the Mid-Atlantic and Midwestern United States. It also provides brokerage and advisory services to commercial customers.", "CEO": "Michael M Stein", "issueType": "cs", "sector": "Energy", "tags": ["Energy", "Oil & Gas E&P", "Oil & Gas - E&P"]}