{"symbol": "GOODM", "companyName": "Gladstone Commercial Corporation Series D Cumulative Redeemable Preferred Stock", "exchange": "Nasdaq Global Select", "industry": "REITs", "website": "http://www.gladstonecommercial.com", "description": "Gladstone Commercial Corp is a real estate investment trust. The company is engaged in investing in and owning net leased industrial, commercial and retail real property and making long-term industrial and commercial mortgage loans.", "CEO": "David Gladstone", "issueType": "ps", "sector": "Real Estate", "tags": ["Real Estate", "REIT - Diversified", "REITs"]}