{"symbol": "GUT", "companyName": "Gabelli Utility Trust (The)", "exchange": "New York Stock Exchange", "industry": "", "website": "http://www.gabelli.com", "description": "The Funds primary investment objective is to achieve long-term growth of capital and income. The Fund will invest in ordinary stock and other securities of foreign and domestic companies involved to a substantial extent in providing products, services or equipment for the generation or distribution of electricity, gas and water and the provisions of telecommunications services or infrastructure operations, such as airports, toll roads and municipal services.", "CEO": "", "issueType": "cs", "sector": "", "tags": ["Financial Services", "Asset Management"]}