{"symbol": "NNDM", "companyName": "Nano Dimension Ltd.", "exchange": "NASDAQ Capital Market", "industry": "Computer Hardware", "website": "http://www.nano-di.com", "description": "Nano Dimension Ltd is engaged in research and development of a three dimensional printer that prints prototypes for electronic circuits and development of nanotechnology based conductive ink, which are products that are necessary to the 3-D printer.", "CEO": "Amit Dror", "issueType": "cs", "sector": "Technology", "tags": ["Technology", "Computer Systems", "Computer Hardware"]}