{"symbol": "FFHL", "companyName": "Fuwei Films (Holdings) Co. Ltd.", "exchange": "NASDAQ Capital Market", "industry": "Packaging & Containers", "website": "http://www.fuweiholdings.com", "description": "Fuwei Films (Holdings) Co Ltd along with its subsidiaries is engaged in the production and distribution of BOPET film, high quality plastic film widely used in packaging, imaging, electronics, electrical and magnetic products in China.", "CEO": "Zengyong Wang", "issueType": "cs", "sector": "Consumer Cyclical", "tags": ["Consumer Cyclical", "Packaging & Containers"]}