{"symbol": "FLHK", "companyName": "Franklin FTSE Hong Kong", "exchange": "NYSE Arca", "industry": "", "website": "http://etf.franklintempleton.com", "description": "The investment seeks to provide investment results that closely correspond, before fees and expenses, to the performance of FTSE Hong Kong RIC Capped Index (the FTSE Hong Kong Capped Index).\n Under normal market conditions, the fund invests at least 80% of its assets in the component securities of the FTSE Hong Kong Capped Index and in depositary receipts representing such securities. The FTSE Hong Kong Capped Index is based on the FTSE Hong Kong Index and is designed to measure the performance of Hong Kong large- and mid-capitalization stocks. The fund is non-diversified.", "CEO": "", "issueType": "", "sector": "", "tags": []}