{"symbol": "KMB", "companyName": "Kimberly-Clark Corporation", "exchange": "New York Stock Exchange", "industry": "Consumer Packaged Goods", "website": "http://www.kimberly-clark.com", "description": "Kimberly-Clark Corp is engaged in the manufacturing and marketing of a range of products made from natural or synthetic fibers using technologies in fibers, nonwovens, and absorbency. It offers personal care, consumer tissue, and K-C professional.", "CEO": "Thomas J. Falk", "issueType": "cs", "sector": "Consumer Defensive", "tags": ["Consumer Defensive", "Household & Personal Products", "Consumer Packaged Goods"]}