{"symbol": "RE", "companyName": "Everest Re Group Ltd.", "exchange": "New York Stock Exchange", "industry": "Insurance - Specialty", "website": "http://www.everestregroup.com", "description": "Everest Re Group Ltd is engaged in the insurance business. Its offering comprises of property and casualty reinsurance & insurance products and services.", "CEO": "Dominic J. Addesso", "issueType": "cs", "sector": "Financial Services", "tags": ["Financial Services", "Insurance - Reinsurance", "Insurance - Specialty"]}