{"symbol": "VNO", "companyName": "Vornado Realty Trust", "exchange": "New York Stock Exchange", "industry": "REITs", "website": "http://www.vno.com", "description": "Vornado Realty Trust is a fully-integrated real estate investment trust. The company owns and has an ownership interest in Class A office and retail properties in New York and Washington, DC. The company receives revenue in the form of rent.", "CEO": "Steven Roth", "issueType": "cs", "sector": "Real Estate", "tags": ["Real Estate", "REIT - Office", "REITs"]}