{"symbol": "VNTR", "companyName": "Venator Materials PLC", "exchange": "New York Stock Exchange", "industry": "Chemicals", "website": "http://www.venatorcorp.com", "description": "Venator Materials PLC is engaged in the manufacturing and marketing of chemical products. Its products include iron oxide, chromium oxide, titanium dioxide and among others. The titanium dioxide generates maximum revenue for the company.", "CEO": "Simon Turner", "issueType": "cs", "sector": "Basic Materials", "tags": ["Basic Materials", "Chemicals"]}