{"symbol": "CENTA", "companyName": "Central Garden & Pet Company Class A Common Stock Nonvoting", "exchange": "Nasdaq Global Select", "industry": "Consumer Packaged Goods", "website": "http://www.central.com", "description": "Central Garden & Pet Co is a marketer and producer of branded products and distributor of third-party products in the pet and lawn and garden supplies industries in the United States.", "CEO": "", "issueType": "cs", "sector": "Consumer Defensive", "tags": ["Consumer Defensive", "Packaged Foods", "Consumer Packaged Goods"]}