{"symbol": "CLDX", "companyName": "Celldex Therapeutics Inc.", "exchange": "Nasdaq Global Select", "industry": "Biotechnology", "website": "http://www.celldex.com", "description": "Celldex Therapeutics Inc is a biopharmaceutical company. The company is engaged in the development and commercialization of immunotherapy technologies for the treatment of cancer and other difficult-to-treat diseases.", "CEO": "Anthony S. Marucci", "issueType": "cs", "sector": "Healthcare", "tags": ["Healthcare", "Biotechnology"]}