{"symbol": "COLM", "companyName": "Columbia Sportswear Company", "exchange": "Nasdaq Global Select", "industry": "Manufacturing - Apparel & Furniture", "website": "http://www.columbia.com", "description": "Columbia Sportswear Co is engaged in designing, sourcing, marketing and distributing outdoor and active lifestyle apparel, footwear, accessories and equipment. It sells under four brands, Columbia, Sorel, Mountain Hardwear, and prAna.", "CEO": "Timothy P. Boyle", "issueType": "cs", "sector": "Consumer Cyclical", "tags": ["Consumer Cyclical", "Apparel Manufacturing", "Manufacturing - Apparel & Furniture"]}