{"symbol": "CSU", "companyName": "Capital Senior Living Corporation", "exchange": "New York Stock Exchange", "industry": "Health Care Providers", "website": "http://www.capitalsenior.com", "description": "Capital Senior Living Corp provides senior living services to the elderly, including independent living, assisted living, skilled nursing and home care services.", "CEO": "Lawrence A. Cohen", "issueType": "cs", "sector": "Healthcare", "tags": ["Healthcare", "Long-Term Care Facilities", "Health Care Providers"]}