{"symbol": "CTAS", "companyName": "Cintas Corporation", "exchange": "Nasdaq Global Select", "industry": "Business Services", "website": "http://www.cintas.com", "description": "Cintas Corp is a provider of corporate identity uniforms. It products include rental and sale of entrance mats, mops, shop towels, and restroom supplies. The company also offers safety supplies, fire-suppression systems maintenance and others.", "CEO": "Scott D. Farmer", "issueType": "cs", "sector": "Industrials", "tags": ["Industrials", "Business Services"]}