{"symbol": "AGZ", "companyName": "iShares Agency Bond", "exchange": "NYSE Arca", "industry": "", "website": "http://www.ishares.com", "description": "The investment seeks to track the investment results of the Bloomberg Barclays U.S. Agency Bond Index.\n The underlying index measures the performance of the agency sector of the U.S. government bond market and is comprised of investment-grade U.S. dollar-denominated publicly-issued government agency bonds or debentures. The fund generally will invest at least 90% of its assets in the component securities of the underlying index.", "CEO": "", "issueType": "et", "sector": "", "tags": []}