{"symbol": "ALK", "companyName": "Alaska Air Group Inc.", "exchange": "New York Stock Exchange", "industry": "Airlines", "website": "http://www.alaskaair.com", "description": "Alaska Air Group Inc operates Alaska, Virgin America and Horizon Air airlines. The company through its subsidiaries provides passenger air, freight and mail services within the state of Alaska and on the West Coast.", "CEO": "Bradley D. Tilden", "issueType": "cs", "sector": "Industrials", "tags": ["Industrials", "Airlines"]}