{"symbol": "AR", "companyName": "Antero Resources Corporation", "exchange": "New York Stock Exchange", "industry": "Oil & Gas - E&P", "website": "http://www.anteroresources.com", "description": "Antero Resources Corp is an independent oil and natural gas company, which acquires, explores, produces, and develops natural gas, natural gas liquids, and oil properties in the United States.", "CEO": "Paul M. Rady", "issueType": "cs", "sector": "Energy", "tags": ["Energy", "Oil & Gas E&P", "Oil & Gas - E&P"]}