{"symbol": "ATI", "companyName": "Allegheny Technologies Incorporated", "exchange": "New York Stock Exchange", "industry": "Industrial Products", "website": "https://www.atimetals.com", "description": "Allegheny Technologies Inc is a diversified specialty metals producer. Its products include titanium and titanium alloys, nickel-based alloys and specialty steels, precision forgings, castings and machined components, and zirconium.", "CEO": "Richard J. Harshman", "issueType": "cs", "sector": "Industrials", "tags": ["Industrials", "Metal Fabrication", "Industrial Products"]}