{"symbol": "DEI", "companyName": "Douglas Emmett Inc.", "exchange": "New York Stock Exchange", "industry": "REITs", "website": "http://www.douglasemmett.com", "description": "Douglas Emmett Inc acquires, develops, and manages office and multifamily properties in United States. The company mainly focuses on owning office buildings in communities with large supply constraints, such as Los Angeles.", "CEO": "Jordan L. Kaplan", "issueType": "cs", "sector": "Real Estate", "tags": ["Real Estate", "REIT - Office", "REITs"]}