{"symbol": "DLX", "companyName": "Deluxe Corporation", "exchange": "New York Stock Exchange", "industry": "Business Services", "website": "http://www.deluxe.com", "description": "Deluxe Corp provides various business solutions. It provides printed forms to businesses, including checks, deposit tickets, billing forms, invoices and personnel forms. It also provides marketing services including web design and hosting.", "CEO": "Lee J. Schram", "issueType": "cs", "sector": "Industrials", "tags": ["Industrials", "Business Services"]}