{"symbol": "DOGZ", "companyName": "Dogness (International) Corporation", "exchange": "NASDAQ Global Market", "industry": "Consumer Packaged Goods", "website": "http://www.dognesspet.com", "description": "Dogness (International) Corp designs, manufactures and distributes pet-related products. The company offers its products to major retail stores and wholesalers around the world.", "CEO": "Silong Chen", "issueType": "cs", "sector": "Consumer Defensive", "tags": ["Consumer Defensive", "Household & Personal Products", "Consumer Packaged Goods"]}