{"symbol": "DS-D", "companyName": "Drive Shack Inc. Pfd Ser D", "exchange": "New York Stock Exchange", "industry": "Travel & Leisure", "website": "http://www.driveshack.com", "description": "Drive Shack Inc. is a owner and operator of golf-related leisure and entertainment businesses. It's operating business segments are Traditional Golf properties, Entertainment Golf venues and Debt Investments.", "CEO": "Sarah L. Watterson", "issueType": "ps", "sector": "Consumer Cyclical", "tags": ["Consumer Cyclical", "Leisure", "Travel & Leisure"]}