{"symbol": "DVD", "companyName": "Dover Motorsports Inc.", "exchange": "New York Stock Exchange", "industry": "Travel & Leisure", "website": "http://www.dovermotorsports.com", "description": "Dover Motorsports Inc is a marketers and promoters of motorsports entertainment. Through its subsidiaries, it owns and operates Dover International Speedway and Nashville Superspeedway. It is also engaged in harness horse racing operations.", "CEO": "Denis Mcglynn", "issueType": "cs", "sector": "Consumer Cyclical", "tags": ["Consumer Cyclical", "Leisure", "Travel & Leisure"]}