{"symbol": "OMI", "companyName": "Owens & Minor Inc.", "exchange": "New York Stock Exchange", "industry": "Medical Distribution", "website": "http://www.owens-minor.com", "description": "Owens & Minor Inc is a healthcare logistics firm distributing low-tech, consumable medical supplies to acute-care hospitals. The company distributes products to healthcare service providers under various brands such as MediChoice and ArcRoyal.", "CEO": "Robert C. Sledd", "issueType": "cs", "sector": "Healthcare", "tags": ["Healthcare", "Medical Distribution"]}