{"symbol": "OTEX", "companyName": "Open Text Corporation", "exchange": "Nasdaq Global Select", "industry": "Application Software", "website": "http://www.opentext.com", "description": "Open Text Corp develops and sells enterprise information management (EIM) software. The company offers EIM software that allows clients to archive, aggregate, retrieve, and search unstructured information for better management.", "CEO": "Mark J. Barrenechea", "issueType": "cs", "sector": "Technology", "tags": ["Technology", "Software - Application", "Application Software"]}