{"symbol": "ECH", "companyName": "iShares Inc. MSCI Chile", "exchange": "Cboe Global Markets EDGX", "industry": "", "website": "http://www.ishares.com", "description": "The investment seeks to track the investment results of the MSCI Chile IMI 25/50 Index.\n The fund generally will invest at least 90% of its assets in the component securities of the underlying index and in investments that have economic characteristics that are substantially identical to the component securities of the underlying index. The underlying index is a free float-adjusted market capitalization index that is designed to measure broad-based equity market performance in Chile. The fund is non-diversified.", "CEO": "", "issueType": "et", "sector": "", "tags": []}