{"symbol": "EDOM", "companyName": "WisdomTree Europe Domestic Economy Fund", "exchange": "Cboe Global Markets EDGX", "industry": "", "website": "http://www.wisdomtree.com", "description": "The investment seeks to track the price and yield performance, before fees and expenses, of the WisdomTree Europe Domestic Economy Index.\n Under normal circumstances, the fund will invest at least 80% of its total assets in component securities of the index and investments that have economic characteristics that are substantially identical to the economic characteristics of such component securities. The index is designed with a goal of maximizing exposure to European companies with significant European revenue that may benefit from an economic recovery in Europe and increased buying power by Europeans. The fund is non-diversified.", "CEO": "", "issueType": "", "sector": "", "tags": []}