{"symbol": "EFII", "companyName": "Electronics for Imaging Inc.", "exchange": "Nasdaq Global Select", "industry": "Computer Hardware", "website": "http://www.efi.com", "description": "Electronics for Imaging Inc is a digital printing innovation company. It provides digital printing services to printer manufacturers, commercial photo labs, sign shops, and billboard graphics providers.", "CEO": "William D. Muir", "issueType": "cs", "sector": "Technology", "tags": ["Technology", "Computer Systems", "Computer Hardware"]}