{"symbol": "ENG", "companyName": "ENGlobal Corporation", "exchange": "NASDAQ Capital Market", "industry": "Engineering & Construction", "website": "http://www.englobal.com", "description": "ENGlobal Corp is a provider of engineering and other professional project services related to design, fabrication, procurement, maintenance, environmental and other governmental compliance and construction management.", "CEO": "William A. Coskey", "issueType": "cs", "sector": "Industrials", "tags": ["Industrials", "Engineering & Construction"]}