{"symbol": "ESRT", "companyName": "Empire State Realty Trust Inc. Class A", "exchange": "New York Stock Exchange", "industry": "REITs", "website": "http://www.empirestaterealtytrust.com", "description": "Empire State Realty Trust Inc owns, operates, acquires and repositions properties such as Empire State Building, One Grand Central Place in Manhattan and the greater New York metropolitan area. It operates in two segments, Real Estate and Observatory.", "CEO": "Anthony E. Malkin", "issueType": "cs", "sector": "Real Estate", "tags": ["Real Estate", "REIT - Diversified", "REITs"]}