{"symbol": "EURN", "companyName": "Euronav NV", "exchange": "New York Stock Exchange", "industry": "Transportation & Logistics", "website": "http://www.euronav.com", "description": "Euronav NV provides international maritime shipping and offshore services engaged in the transportation and storage of crude oil. The company owns and operates modern fleet of around 55 vessels.", "CEO": "", "issueType": "cs", "sector": "Industrials", "tags": ["Industrials", "Integrated Shipping & Logistics", "Transportation & Logistics"]}