{"symbol": "JPUS", "companyName": "JPMorgan Diversified Return U.S. Equity", "exchange": "NYSE Arca", "industry": "", "website": "", "description": "The investment seeks investment results that closely correspond, to the performance of the JP Morgan Diversified Factor Europe Currency Hedged (USD) Index.\n The fund principally invests in the JPMorgan Diversified Return Europe Equity ETF and forward foreign currency contracts. The underlying index has been developed to represent European stock performance, with the foreign currency risk of the securities included in the underlying index hedged against the U.S. dollar on a monthly basis. The underlying index is comprised of equity securities across developed Europe selected to represent a diversified set of factor characteristics: value, momentum, and quality.", "CEO": "", "issueType": "", "sector": "", "tags": []}