{"symbol": "MATX", "companyName": "Matson Inc.", "exchange": "New York Stock Exchange", "industry": "Transportation & Logistics", "website": "http://www.matson.com", "description": "Matson Inc is a holding company, consisting of two segments, ocean transportation and logistics. The company also provides container stevedoring, container equipment maintenance and other terminal services for MatNav and other ocean carriers.", "CEO": "Matthew J. Cox", "issueType": "cs", "sector": "Industrials", "tags": ["Industrials", "Shipping & Ports", "Transportation & Logistics"]}