{"symbol": "MDCO", "companyName": "The Medicines Company", "exchange": "Nasdaq Global Select", "industry": "Drug Manufacturers", "website": "http://www.themedicinescompany.com", "description": "The Medicines Co is a pharmaceutical company. It provides transformational solutions to address the most pressing healthcare needs facing patients, physicians and providers. The company's products are Angiomax, Ionsys, Minocin for injection and Orbactiv.", "CEO": "Clive A. Meanwell", "issueType": "cs", "sector": "Healthcare", "tags": ["Healthcare", "Drug Manufacturers - Specialty & Generic", "Drug Manufacturers"]}