{"symbol": "MEDP", "companyName": "Medpace Holdings Inc.", "exchange": "Nasdaq Global Select", "industry": "Medical Diagnostics & Research", "website": "http://www.medpace.com", "description": "Medpace Holdings Inc is a clinical contract research organisation. It is engaged in providing scientifically-driven clinical research-based drug and medical device development services to the biotechnology, pharmaceutical and medical device industries.", "CEO": "August J. Troendle", "issueType": "cs", "sector": "Healthcare", "tags": ["Healthcare", "Diagnostics & Research", "Medical Diagnostics & Research"]}