{"symbol": "MOV", "companyName": "Movado Group Inc.", "exchange": "New York Stock Exchange", "industry": "Retail - Apparel & Specialty", "website": "http://www.movadogroup.com", "description": "Movado Group Inc designs, sources, markets and distributes fine watches. Its brands include Coach Watches, Concord, Ebel, ESQ Movado, Scuderia Ferrari Watches, HUGO BOSS Watches, Juicy Couture Watches, Lacoste Watches, Movado, and Tommy Hilfiger Watches.", "CEO": "Efraim Grinberg", "issueType": "cs", "sector": "Consumer Cyclical", "tags": ["Consumer Cyclical", "Luxury Goods", "Retail - Apparel & Specialty"]}