{"symbol": "MTH", "companyName": "Meritage Homes Corporation", "exchange": "New York Stock Exchange", "industry": "Homebuilding & Construction", "website": "http://www.meritagehomes.com", "description": "Meritage Homes Corp is a designer and builder of single-family homes. The company offer homes that are designed to appeal to a wide range of homebuyers primarily focused on first-time and first move-up buyers. Its operations are spread across USA.", "CEO": "Steven J. Hilton", "issueType": "cs", "sector": "Consumer Cyclical", "tags": ["Consumer Cyclical", "Residential Construction", "Homebuilding & Construction"]}