{"symbol": "HBI", "companyName": "Hanesbrands Inc.", "exchange": "New York Stock Exchange", "industry": "Manufacturing - Apparel & Furniture", "website": "http://www.hanes.com/corporate", "description": "Hanesbrands Inc designs, manufactures, sources and sells apparel essentials such as t-shirts, innerwear, casualwear, activewear, socks and hosiery. It markets its products under the brand names of Hanes, Champion, and Maidenform.", "CEO": "Gerald Evans", "issueType": "cs", "sector": "Consumer Cyclical", "tags": ["Consumer Cyclical", "Apparel Manufacturing", "Manufacturing - Apparel & Furniture"]}