{"symbol": "HFBL", "companyName": "Home Federal Bancorp Inc. of Louisiana", "exchange": "NASDAQ Capital Market", "industry": "Banks", "website": "http://www.homefederalbancorp.com", "description": "Home Federal Bancorp Inc of louisiana operates as the holding company for Home Federal Bank. It offers financial services to individuals, corporate entities and other organizations in northwest Louisiana.", "CEO": "James R. Barlow", "issueType": "cs", "sector": "Financial Services", "tags": ["Financial Services", "Savings & Cooperative Banks", "Banks"]}