{"symbol": "IDMO", "companyName": "Invesco S&P International Developed Momentum", "exchange": "NYSE Arca", "industry": "", "website": "http://www.invescopowershares.com", "description": "The investment seeks to track the investment results (before fees and expenses) of the S&P Momentum Developed ex-U.S. & South Korea LargeMidCap IndexTM (the \"underlying index\").\n The fund will invest at least 90% of its total assets in the securities of companies that comprise the underlying index. Strictly in accordance with its guidelines and mandated procedures, the index provider compiles, maintains and calculates the underlying index, which is composed of constituents of the S&P Developed ex-U.S. & South Korea LargeMidCap Index that have the highest \"momentum score.\"", "CEO": "", "issueType": "et", "sector": "", "tags": []}