{"symbol": "BCOV", "companyName": "Brightcove Inc.", "exchange": "Nasdaq Global Select", "industry": "Application Software", "website": "http://www.brightcove.com", "description": "Brightcove Inc offers cloud solutions to deliver and monetize video across connected devices. The company supports its clients to effectively operate their businesses be it broadcasting, publishing, marketing, or enterprise communications.", "CEO": "Hugh Jefferson Ray", "issueType": "cs", "sector": "Technology", "tags": ["Technology", "Software - Application", "Application Software"]}