{"symbol": "BG", "companyName": "Bunge Limited", "exchange": "New York Stock Exchange", "industry": "Consumer Packaged Goods", "website": "http://www.bunge.com", "description": "Bunge Ltd is an agribusiness and food company with integrated operations. It acts as an oilseed processor and seller of packaged vegetable oils. The company also grows and processes Brazilian sugarcane to produce sugar and ethanol.", "CEO": "Soren Schroder", "issueType": "cs", "sector": "Consumer Defensive", "tags": ["Consumer Defensive", "Farm Products", "Consumer Packaged Goods"]}