{"symbol": "BIOL", "companyName": "Biolase Inc.", "exchange": "NASDAQ Capital Market", "industry": "Medical Instruments & Equipment", "website": "http://www.biolase.com", "description": "Biolase Inc is a medical device company that develops, manufactures, and markets lasers in dentistry and medicine and also markets and distributes dental imaging equipment.", "CEO": "Todd Norbe", "issueType": "cs", "sector": "Healthcare", "tags": ["Healthcare", "Medical Instruments & Supplies", "Medical Instruments & Equipment"]}