{"symbol": "BMA", "companyName": "Banco Macro S.A. ADR (representing Ten Class B)", "exchange": "New York Stock Exchange", "industry": "Banks", "website": "http://www.macro.com.ar", "description": "Banco Macro SA is a commercial bank standard banking products and services. It provides its service to retail customer and small to medium-size businesses.", "CEO": "Gustavo Alejandro Manriquez", "issueType": "cs", "sector": "Financial Services", "tags": ["Financial Services", "Banks - Regional - Latin America", "Banks"]}