{"symbol": "WCFB", "companyName": "WCF Bancorp Inc.", "exchange": "NASDAQ Capital Market", "industry": "Banks", "website": "http://www.wcfbank.com", "description": "WCF Bancorp Inc is engaged in accepting deposits from the general public and investing those deposits, together with funds generated from operations and borrowings, in real estate loans secured by one-to-four family residences.", "CEO": "Michael R. Segner", "issueType": "cs", "sector": "Financial Services", "tags": ["Financial Services", "Banks - Regional - US", "Banks"]}