{"symbol": "WDC", "companyName": "Western Digital Corporation", "exchange": "Nasdaq Global Select", "industry": "Computer Hardware", "website": "https://www.wdc.com", "description": "Western Digital Corp is the global leader in the hard disk drive market. It develops, manufactures, and provides data storage solutions that enable consumers to create, manage, experience and preserve digital content. Its products include HDDs and SSDs.", "CEO": "Stephen D. Milligan", "issueType": "cs", "sector": "Technology", "tags": ["Technology", "Data Storage", "Computer Hardware"]}