{"symbol": "WSO", "companyName": "Watsco Inc.", "exchange": "New York Stock Exchange", "industry": "Computer Hardware", "website": "http://www.watsco.com", "description": "Watsco Inc distributes air conditioning, heating and refrigeration equipment and related parts and supplies in the HVAC/R distribution industry in North America. Watsco has operations in the United States, Canada, Mexico and Puerto Rico.", "CEO": "Albert H. Nahmad", "issueType": "cs", "sector": "Technology", "tags": ["Technology", "Electronics Distribution", "Computer Hardware"]}