{"symbol": "UBFO", "companyName": "United Security Bancshares", "exchange": "Nasdaq Global Select", "industry": "Banks", "website": "http://www.unitedsecuritybank.com", "description": "United Security Bancshares operates as the holding for United Security Bank. It provides commercial banking services to the business and professional community, and individuals located in Fresno, Madera, and Kern Counties.", "CEO": "Dennis R. Woods", "issueType": "cs", "sector": "Financial Services", "tags": ["Financial Services", "Banks - Regional - US", "Banks"]}