{"symbol": "UG", "companyName": "United-Guardian Inc.", "exchange": "NASDAQ Global Market", "industry": "Consumer Packaged Goods", "website": "http://www.u-g.com", "description": "United-Guardian Inc is a manufacturer and distributor of personal care products such as cosmetics mainly in the United States. Its portfolio also includes pharmaceuticals, medical lubricants, healthcare solutions.", "CEO": "Kenneth H. Globus", "issueType": "cs", "sector": "Consumer Defensive", "tags": ["Consumer Defensive", "Household & Personal Products", "Consumer Packaged Goods"]}