{"symbol": "UTSI", "companyName": "UTStarcom Holdings Corp", "exchange": "Nasdaq Global Select", "industry": "Communication Services", "website": "http://www.utstar.com", "description": "UTStarcom Holdings Corp is a telecom infrastructure provider. The company is engaged in developing technology that will serve the rapidly growing demand for bandwidth from mobile, streaming and other applications.", "CEO": "Tim Ti", "issueType": "cs", "sector": "Communication Services", "tags": ["Communication Services", "Telecom Services"]}